{"get": "fixtures/players", "parameters": {"fixture": "1591865"}, "errors": [], "results": 2, "paging": {"current": 1, "total": 1}, "response": [{"team": {"id": 2, "name": "France", "logo": "https://media.api-sports.io/football/teams/2.png", "update": "2026-07-21T04:07:07+00:00"}, "players": [{"player": {"id": 22221, "name": "Mike Maignan", "photo": "https://media.api-sports.io/football/players/22221.png"}, "statistics": [{"games": {"minutes": 90, "number": 16, "position": "G", "rating": "6", "captain": false, "substitute": false}, "offsides": null, "shots": {"total": null, "on": null}, "goals": {"total": null, "conceded": 6, "assists": 0, "saves": 4}, "passes": {"total": 12, "key": null, "accuracy": "11"}, "tackles": {"total": null, "blocks": null, "interceptions": null}, "duels": {"total": 1, "won": null}, "dribbles": {"attempts": null, "success": null, "past": 1}, "fouls": {"drawn": null, "committed": null}, "cards": {"yellow": 0, "red": 0}, "penalty": {"won": null, "commited": null, "scored": 0, "missed": 0, "saved": 0}}]}, {"player": {"id": 161907, "name": "Malo Gusto", "photo": "https://media.api-sports.io/football/players/161907.png"}, "statistics": [{"games": {"minutes": 89, "number": 2, "position": "D", "rating": "5.3", "captain": false, "substitute": false}, "offsides": null, "shots": {"total": null, "on": null}, "goals": {"total": null, "conceded": 0, "assists": 0, "saves": null}, "passes": {"total": 42, "key": null, "accuracy": "36"}, "tackles": {"total": 3, "blocks": 2, "interceptions": 1}, "duels": {"total": 11, "won": 5}, "dribbles": {"attempts": 1, "success": null, "past": 3}, "fouls": {"drawn": 2, "committed": 2}, "cards": {"yellow": 0, "red": 0}, "penalty": {"won": null, "commited": 1, "scored": 0, "missed": 0, "saved": null}}]}, {"player": {"id": 1145, "name": "Ibrahima Konaté", "photo": "https://media.api-sports.io/football/players/1145.png"}, "statistics": [{"games": {"minutes": 45, "number": 15, "position": "D", "rating": "5.3", "captain": false, "substitute": false}, "offsides": null, "shots": {"total": null, "on": null}, "goals": {"total": null, "conceded": 0, "assists": 0, "saves": null}, "passes": {"total": 23, "key": null, "accuracy": "21"}, "tackles": {"total": null, "blocks": null, "interceptions": null}, "duels": {"total": 4, "won": 1}, "dribbles": {"attempts": null, "success": null, "past": null}, "fouls": {"drawn": 1, "committed": 2}, "cards": {"yellow": 0, "red": 0}, "penalty": {"won": null, "commited": null, "scored": 0, "missed": 0, "saved": null}}]}, {"player": {"id": 20995, "name": "Maxence Lacroix", "photo": "https://media.api-sports.io/football/players/20995.png"}, "statistics": [{"games": {"minutes": 90, "number": 26, "position": "D", "rating": "7.5", "captain": false, "substitute": false}, "offsides": null, "shots": {"total": null, "on": null}, "goals": {"total": null, "conceded": 0, "assists": 0, "saves": null}, "passes": {"total": 35, "key": null, "accuracy": "34"}, "tackles": {"total": 1, "blocks": 4, "interceptions": 1}, "duels": {"total": 10, "won": 7}, "dribbles": {"attempts": 1, "success": 1, "past": 1}, "fouls": {"drawn": null, "committed": 1}, "cards": {"yellow": 0, "red": 0}, "penalty": {"won": null, "commited": null, "scored": 0, "missed": 0, "saved": null}}]}, {"player": {"id": 47300, "name": "Theo Hernández", "photo": "https://media.api-sports.io/football/players/47300.png"}, "statistics": [{"games": {"minutes": 45, "number": 19, "position": "D", "rating": "5.9", "captain": false, "substitute": false}, "offsides": null, "shots": {"total": null, "on": null}, "goals": {"total": null, "conceded": 0, "assists": 0, "saves": null}, "passes": {"total": 24, "key": null, "accuracy": "20"}, "tackles": {"total": null, "blocks": 1, "interceptions": 1}, "duels": {"total": null, "won": null}, "dribbles": {"attempts": null, "success": null, "past": null}, "fouls": {"drawn": null, "committed": null}, "cards": {"yellow": 0, "red": 0}, "penalty": {"won": null, "commited": null, "scored": 0, "missed": 0, "saved": null}}]}, {"player": {"id": 336657, "name": "Warren Zaïre-Emery", "photo": "https://media.api-sports.io/football/players/336657.png"}, "statistics": [{"games": {"minutes": 90, "number": 18, "position": "M", "rating": "6.7", "captain": false, "substitute": false}, "offsides": null, "shots": {"total": null, "on": null}, "goals": {"total": null, "conceded": 0, "assists": 0, "saves": null}, "passes": {"total": 57, "key": 2, "accuracy": "54"}, "tackles": {"total": null, "blocks": null, "interceptions": null}, "duels": {"total": 4, "won": 1}, "dribbles": {"attempts": null, "success": null, "past": 1}, "fouls": {"drawn": null, "committed": null}, "cards": {"yellow": 0, "red": 0}, "penalty": {"won": null, "commited": null, "scored": 0, "missed": 0, "saved": null}}]}, {"player": {"id": 272, "name": "Adrien Rabiot", "photo": "https://media.api-sports.io/football/players/272.png"}, "statistics": [{"games": {"minutes": 90, "number": 14, "position": "M", "rating": "6.3", "captain": false, "substitute": false}, "offsides": null, "shots": {"total": 1, "on": null}, "goals": {"total": null, "conceded": 0, "assists": 0, "saves": null}, "passes": {"total": 39, "key": 2, "accuracy": "37"}, "tackles": {"total": 2, "blocks": null, "interceptions": 2}, "duels": {"total": 10, "won": 3}, "dribbles": {"attempts": 1, "success": null, "past": 2}, "fouls": {"drawn": 1, "committed": 2}, "cards": {"yellow": 0, "red": 0}, "penalty": {"won": null, "commited": null, "scored": 0, "missed": 0, "saved": null}}]}, {"player": {"id": 19617, "name": "Michael Olise", "photo": "https://media.api-sports.io/football/players/19617.png"}, "statistics": [{"games": {"minutes": 90, "number": 11, "position": "M", "rating": "7", "captain": false, "substitute": false}, "offsides": null, "shots": {"total": 3, "on": null}, "goals": {"total": null, "conceded": 0, "assists": 2, "saves": null}, "passes": {"total": 56, "key": 4, "accuracy": "49"}, "tackles": {"total": 5, "blocks": null, "interceptions": null}, "duels": {"total": 14, "won": 6}, "dribbles": {"attempts": 5, "success": 1, "past": 2}, "fouls": {"drawn": null, "committed": 1}, "cards": {"yellow": 0, "red": 0}, "penalty": {"won": null, "commited": null, "scored": 0, "missed": 0, "saved": null}}]}, {"player": {"id": 156477, "name": "Rayan Cherki", "photo": "https://media.api-sports.io/football/players/156477.png"}, "statistics": [{"games": {"minutes": 45, "number": 24, "position": "M", "rating": "6.5", "captain": false, "substitute": false}, "offsides": null, "shots": {"total": 1, "on": 1}, "goals": {"total": null, "conceded": 0, "assists": 0, "saves": null}, "passes": {"total": 29, "key": null, "accuracy": "25"}, "tackles": {"total": null, "blocks": null, "interceptions": null}, "duels": {"total": 2, "won": 1}, "dribbles": {"attempts": null, "success": null, "past": null}, "fouls": {"drawn": 1, "committed": null}, "cards": {"yellow": 0, "red": 0}, "penalty": {"won": null, "commited": null, "scored": 0, "missed": 0, "saved": null}}]}, {"player": {"id": 343027, "name": "Désiré Doué", "photo": "https://media.api-sports.io/football/players/343027.png"}, "statistics": [{"games": {"minutes": 45, "number": 20, "position": "M", "rating": "5.9", "captain": false, "substitute": false}, "offsides": null, "shots": {"total": null, "on": null}, "goals": {"total": null, "conceded": 0, "assists": 0, "saves": null}, "passes": {"total": 20, "key": null, "accuracy": "19"}, "tackles": {"total": 1, "blocks": null, "interceptions": null}, "duels": {"total": 7, "won": 4}, "dribbles": {"attempts": 2, "success": 1, "past": 1}, "fouls": {"drawn": 2, "committed": 1}, "cards": {"yellow": 0, "red": 0}, "penalty": {"won": null, "commited": null, "scored": 0, "missed": 0, "saved": null}}]}, {"player": {"id": 278, "name": "Kylian Mbappé", "photo": "https://media.api-sports.io/football/players/278.png"}, "statistics": [{"games": {"minutes": 90, "number": 10, "position": "F", "rating": "10", "captain": true, "substitute": false}, "offsides": 2, "shots": {"total": 6, "on": 4}, "goals": {"total": 2, "conceded": 0, "assists": 1, "saves": null}, "passes": {"total": 32, "key": 2, "accuracy": "28"}, "tackles": {"total": null, "blocks": null, "interceptions": null}, "duels": {"total": 15, "won": 2}, "dribbles": {"attempts": 7, "success": 2, "past": 2}, "fouls": {"drawn": null, "committed": null}, "cards": {"yellow": 0, "red": 0}, "penalty": {"won": null, "commited": null, "scored": 0, "missed": 0, "saved": null}}]}, {"player": {"id": 1149, "name": "Dayot Upamecano", "photo": "https://media.api-sports.io/football/players/1149.png"}, "statistics": [{"games": {"minutes": 45, "number": 4, "position": "D", "rating": "6.5", "captain": false, "substitute": true}, "offsides": null, "shots": {"total": 1, "on": 1}, "goals": {"total": null, "conceded": 0, "assists": 1, "saves": null}, "passes": {"total": 13, "key": 1, "accuracy": "12"}, "tackles": {"total": 3, "blocks": null, "interceptions": 2}, "duels": {"total": 9, "won": 3}, "dribbles": {"attempts": null, "success": null, "past": 5}, "fouls": {"drawn": null, "committed": 1}, "cards": {"yellow": 0, "red": 0}, "penalty": {"won": null, "commited": null, "scored": 0, "missed": 0, "saved": null}}]}, {"player": {"id": 2724, "name": "Lucas Digne", "photo": "https://media.api-sports.io/football/players/2724.png"}, "statistics": [{"games": {"minutes": 45, "number": 3, "position": "D", "rating": "6.3", "captain": false, "substitute": true}, "offsides": null, "shots": {"total": null, "on": null}, "goals": {"total": null, "conceded": 0, "assists": 0, "saves": null}, "passes": {"total": 18, "key": null, "accuracy": "17"}, "tackles": {"total": null, "blocks": null, "interceptions": 1}, "duels": {"total": 6, "won": 3}, "dribbles": {"attempts": 1, "success": null, "past": null}, "fouls": {"drawn": null, "committed": 2}, "cards": {"yellow": 0, "red": 0}, "penalty": {"won": null, "commited": null, "scored": 0, "missed": 0, "saved": null}}]}, {"player": {"id": 153, "name": "Ousmane Dembélé", "photo": "https://media.api-sports.io/football/players/153.png"}, "statistics": [{"games": {"minutes": 45, "number": 7, "position": "F", "rating": "8.2", "captain": false, "substitute": true}, "offsides": 1, "shots": {"total": 2, "on": 2}, "goals": {"total": 1, "conceded": 0, "assists": 0, "saves": null}, "passes": {"total": 28, "key": 2, "accuracy": "25"}, "tackles": {"total": null, "blocks": null, "interceptions": null}, "duels": {"total": 3, "won": 2}, "dribbles": {"attempts": 1, "success": 1, "past": 1}, "fouls": {"drawn": 1, "committed": null}, "cards": {"yellow": 0, "red": 0}, "penalty": {"won": null, "commited": null, "scored": 0, "missed": 0, "saved": null}}]}, {"player": {"id": 161904, "name": "Bradley Barcola", "photo": "https://media.api-sports.io/football/players/161904.png"}, "statistics": [{"games": {"minutes": 45, "number": 12, "position": "F", "rating": "7.9", "captain": false, "substitute": true}, "offsides": null, "shots": {"total": 1, "on": 1}, "goals": {"total": 1, "conceded": 0, "assists": 0, "saves": null}, "passes": {"total": 12, "key": 1, "accuracy": "12"}, "tackles": {"total": 1, "blocks": null, "interceptions": null}, "duels": {"total": 6, "won": 2}, "dribbles": {"attempts": 1, "success": 1, "past": 1}, "fouls": {"drawn": null, "committed": 2}, "cards": {"yellow": 0, "red": 0}, "penalty": {"won": null, "commited": null, "scored": 0, "missed": 0, "saved": null}}]}, {"player": {"id": 1257, "name": "Jules Koundé", "photo": "https://media.api-sports.io/football/players/1257.png"}, "statistics": [{"games": {"minutes": 8, "number": 5, "position": "D", "rating": "6.2", "captain": false, "substitute": true}, "offsides": null, "shots": {"total": null, "on": null}, "goals": {"total": null, "conceded": 0, "assists": 0, "saves": null}, "passes": {"total": 5, "key": null, "accuracy": "5"}, "tackles": {"total": null, "blocks": null, "interceptions": null}, "duels": {"total": 1, "won": null}, "dribbles": {"attempts": null, "success": null, "past": 1}, "fouls": {"drawn": null, "committed": null}, "cards": {"yellow": 0, "red": 0}, "penalty": {"won": null, "commited": null, "scored": 0, "missed": 0, "saved": null}}]}, {"player": {"id": 347211, "name": "Robin Risser", "photo": "https://media.api-sports.io/football/players/347211.png"}, "statistics": [{"games": {"minutes": null, "number": 23, "position": "G", "rating": null, "captain": false, "substitute": true}, "offsides": null, "shots": {"total": null, "on": null}, "goals": {"total": null, "conceded": 0, "assists": null, "saves": null}, "passes": {"total": null, "key": null, "accuracy": null}, "tackles": {"total": null, "blocks": null, "interceptions": null}, "duels": {"total": null, "won": null}, "dribbles": {"attempts": null, "success": null, "past": null}, "fouls": {"drawn": null, "committed": null}, "cards": {"yellow": 0, "red": 0}, "penalty": {"won": null, "commited": null, "scored": 0, "missed": 0, "saved": null}}]}, {"player": {"id": 21628, "name": "Brice Samba", "photo": "https://media.api-sports.io/football/players/21628.png"}, "statistics": [{"games": {"minutes": null, "number": 1, "position": "G", "rating": null, "captain": false, "substitute": true}, "offsides": null, "shots": {"total": null, "on": null}, "goals": {"total": null, "conceded": 0, "assists": null, "saves": null}, "passes": {"total": null, "key": null, "accuracy": null}, "tackles": {"total": null, "blocks": null, "interceptions": null}, "duels": {"total": null, "won": null}, "dribbles": {"attempts": null, "success": null, "past": null}, "fouls": {"drawn": null, "committed": null}, "cards": {"yellow": 0, "red": 0}, "penalty": {"won": null, "commited": null, "scored": 0, "missed": 0, "saved": null}}]}, {"player": {"id": 33, "name": "Lucas Hernández", "photo": "https://media.api-sports.io/football/players/33.png"}, "statistics": [{"games": {"minutes": null, "number": 21, "position": "D", "rating": null, "captain": false, "substitute": true}, "offsides": null, "shots": {"total": null, "on": null}, "goals": {"total": null, "conceded": 0, "assists": null, "saves": null}, "passes": {"total": null, "key": null, "accuracy": null}, "tackles": {"total": null, "blocks": null, "interceptions": null}, "duels": {"total": null, "won": null}, "dribbles": {"attempts": null, "success": null, "past": null}, "fouls": {"drawn": null, "committed": null}, "cards": {"yellow": 0, "red": 0}, "penalty": {"won": null, "commited": null, "scored": 0, "missed": 0, "saved": null}}]}, {"player": {"id": 22090, "name": "William Saliba", "photo": "https://media.api-sports.io/football/players/22090.png"}, "statistics": [{"games": {"minutes": null, "number": 17, "position": "D", "rating": null, "captain": false, "substitute": true}, "offsides": null, "shots": {"total": null, "on": null}, "goals": {"total": null, "conceded": 0, "assists": null, "saves": null}, "passes": {"total": null, "key": null, "accuracy": null}, "tackles": {"total": null, "blocks": null, "interceptions": null}, "duels": {"total": null, "won": null}, "dribbles": {"attempts": null, "success": null, "past": null}, "fouls": {"drawn": null, "committed": null}, "cards": {"yellow": 0, "red": 0}, "penalty": {"won": null, "commited": null, "scored": 0, "missed": 0, "saved": null}}]}, {"player": {"id": 1271, "name": "Aurélien Tchouaméni", "photo": "https://media.api-sports.io/football/players/1271.png"}, "statistics": [{"games": {"minutes": null, "number": 8, "position": "M", "rating": null, "captain": false, "substitute": true}, "offsides": null, "shots": {"total": null, "on": null}, "goals": {"total": null, "conceded": 0, "assists": null, "saves": null}, "passes": {"total": null, "key": null, "accuracy": null}, "tackles": {"total": null, "blocks": null, "interceptions": null}, "duels": {"total": null, "won": null}, "dribbles": {"attempts": null, "success": null, "past": null}, "fouls": {"drawn": null, "committed": null}, "cards": {"yellow": 0, "red": 0}, "penalty": {"won": null, "commited": null, "scored": 0, "missed": 0, "saved": null}}]}, {"player": {"id": 274300, "name": "Maghnes Akliouche", "photo": "https://media.api-sports.io/football/players/274300.png"}, "statistics": [{"games": {"minutes": null, "number": 25, "position": "M", "rating": null, "captain": false, "substitute": true}, "offsides": null, "shots": {"total": null, "on": null}, "goals": {"total": null, "conceded": 0, "assists": null, "saves": null}, "passes": {"total": null, "key": null, "accuracy": null}, "tackles": {"total": null, "blocks": null, "interceptions": null}, "duels": {"total": null, "won": null}, "dribbles": {"attempts": null, "success": null, "past": null}, "fouls": {"drawn": null, "committed": null}, "cards": {"yellow": 0, "red": 0}, "penalty": {"won": null, "commited": null, "scored": 0, "missed": 0, "saved": null}}]}, {"player": {"id": 22147, "name": "Manu Koné", "photo": "https://media.api-sports.io/football/players/22147.png"}, "statistics": [{"games": {"minutes": null, "number": 6, "position": "M", "rating": null, "captain": false, "substitute": true}, "offsides": null, "shots": {"total": null, "on": null}, "goals": {"total": null, "conceded": 0, "assists": null, "saves": null}, "passes": {"total": null, "key": null, "accuracy": null}, "tackles": {"total": null, "blocks": null, "interceptions": null}, "duels": {"total": null, "won": null}, "dribbles": {"attempts": null, "success": null, "past": null}, "fouls": {"drawn": null, "committed": null}, "cards": {"yellow": 0, "red": 0}, "penalty": {"won": null, "commited": null, "scored": 0, "missed": 0, "saved": null}}]}, {"player": {"id": 2290, "name": "N'Golo Kanté", "photo": "https://media.api-sports.io/football/players/2290.png"}, "statistics": [{"games": {"minutes": null, "number": 13, "position": "M", "rating": null, "captain": false, "substitute": true}, "offsides": null, "shots": {"total": null, "on": null}, "goals": {"total": null, "conceded": 0, "assists": null, "saves": null}, "passes": {"total": null, "key": null, "accuracy": null}, "tackles": {"total": null, "blocks": null, "interceptions": null}, "duels": {"total": null, "won": null}, "dribbles": {"attempts": null, "success": null, "past": null}, "fouls": {"drawn": null, "committed": null}, "cards": {"yellow": 0, "red": 0}, "penalty": {"won": null, "commited": null, "scored": 0, "missed": 0, "saved": null}}]}, {"player": {"id": 25927, "name": "Jean-Philippe Mateta", "photo": "https://media.api-sports.io/football/players/25927.png"}, "statistics": [{"games": {"minutes": null, "number": 22, "position": "F", "rating": null, "captain": false, "substitute": true}, "offsides": null, "shots": {"total": null, "on": null}, "goals": {"total": null, "conceded": 0, "assists": null, "saves": null}, "passes": {"total": null, "key": null, "accuracy": null}, "tackles": {"total": null, "blocks": null, "interceptions": null}, "duels": {"total": null, "won": null}, "dribbles": {"attempts": null, "success": null, "past": null}, "fouls": {"drawn": null, "committed": null}, "cards": {"yellow": 0, "red": 0}, "penalty": {"won": null, "commited": null, "scored": 0, "missed": 0, "saved": null}}]}, {"player": {"id": 21509, "name": "Marcus Thuram", "photo": "https://media.api-sports.io/football/players/21509.png"}, "statistics": [{"games": {"minutes": null, "number": 9, "position": "F", "rating": null, "captain": false, "substitute": true}, "offsides": null, "shots": {"total": null, "on": null}, "goals": {"total": null, "conceded": 0, "assists": null, "saves": null}, "passes": {"total": null, "key": null, "accuracy": null}, "tackles": {"total": null, "blocks": null, "interceptions": null}, "duels": {"total": null, "won": null}, "dribbles": {"attempts": null, "success": null, "past": null}, "fouls": {"drawn": null, "committed": null}, "cards": {"yellow": 0, "red": 0}, "penalty": {"won": null, "commited": null, "scored": 0, "missed": 0, "saved": null}}]}]}, {"team": {"id": 10, "name": "England", "logo": "https://media.api-sports.io/football/teams/10.png", "update": "2026-07-21T04:07:07+00:00"}, "players": [{"player": {"id": 19088, "name": "Dean Henderson", "photo": "https://media.api-sports.io/football/players/19088.png"}, "statistics": [{"games": {"minutes": 90, "number": 13, "position": "G", "rating": "7", "captain": false, "substitute": false}, "offsides": null, "shots": {"total": null, "on": null}, "goals": {"total": null, "conceded": 4, "assists": 0, "saves": 5}, "passes": {"total": 37, "key": null, "accuracy": "28"}, "tackles": {"total": null, "blocks": null, "interceptions": 1}, "duels": {"total": null, "won": null}, "dribbles": {"attempts": null, "success": null, "past": null}, "fouls": {"drawn": null, "committed": null}, "cards": {"yellow": 0, "red": 0}, "penalty": {"won": null, "commited": null, "scored": 0, "missed": 0, "saved": 0}}]}, {"player": {"id": 158698, "name": "Jarell Quansah", "photo": "https://media.api-sports.io/football/players/158698.png"}, "statistics": [{"games": {"minutes": 83, "number": 26, "position": "D", "rating": "6.2", "captain": false, "substitute": false}, "offsides": null, "shots": {"total": null, "on": null}, "goals": {"total": null, "conceded": 0, "assists": 0, "saves": null}, "passes": {"total": 35, "key": null, "accuracy": "32"}, "tackles": {"total": 1, "blocks": null, "interceptions": null}, "duels": {"total": 6, "won": 3}, "dribbles": {"attempts": null, "success": null, "past": 2}, "fouls": {"drawn": 2, "committed": 1}, "cards": {"yellow": 0, "red": 0}, "penalty": {"won": null, "commited": null, "scored": 0, "missed": 0, "saved": null}}]}, {"player": {"id": 19354, "name": "Ezri Konsa", "photo": "https://media.api-sports.io/football/players/19354.png"}, "statistics": [{"games": {"minutes": 90, "number": 2, "position": "D", "rating": "7.3", "captain": false, "substitute": false}, "offsides": null, "shots": {"total": 1, "on": 1}, "goals": {"total": 1, "conceded": 0, "assists": 0, "saves": null}, "passes": {"total": 47, "key": null, "accuracy": "45"}, "tackles": {"total": 2, "blocks": 1, "interceptions": 4}, "duels": {"total": 7, "won": 5}, "dribbles": {"attempts": 1, "success": 1, "past": null}, "fouls": {"drawn": null, "committed": 1}, "cards": {"yellow": 0, "red": 0}, "penalty": {"won": null, "commited": null, "scored": 0, "missed": 0, "saved": null}}]}, {"player": {"id": 67971, "name": "Marc Guéhi", "photo": "https://media.api-sports.io/football/players/67971.png"}, "statistics": [{"games": {"minutes": 89, "number": 6, "position": "D", "rating": "7.2", "captain": false, "substitute": false}, "offsides": null, "shots": {"total": null, "on": null}, "goals": {"total": null, "conceded": 0, "assists": 0, "saves": null}, "passes": {"total": 77, "key": 1, "accuracy": "72"}, "tackles": {"total": 2, "blocks": null, "interceptions": 2}, "duels": {"total": 5, "won": 4}, "dribbles": {"attempts": 1, "success": 1, "past": null}, "fouls": {"drawn": 1, "committed": 1}, "cards": {"yellow": 0, "red": 0}, "penalty": {"won": null, "commited": null, "scored": 0, "missed": 0, "saved": null}}]}, {"player": {"id": 19235, "name": "Djed Spence", "photo": "https://media.api-sports.io/football/players/19235.png"}, "statistics": [{"games": {"minutes": 90, "number": 25, "position": "D", "rating": "6.9", "captain": false, "substitute": false}, "offsides": null, "shots": {"total": null, "on": null}, "goals": {"total": null, "conceded": 0, "assists": 0, "saves": null}, "passes": {"total": 37, "key": null, "accuracy": "32"}, "tackles": {"total": 4, "blocks": null, "interceptions": 1}, "duels": {"total": 14, "won": 9}, "dribbles": {"attempts": 4, "success": 3, "past": null}, "fouls": {"drawn": 2, "committed": 2}, "cards": {"yellow": 0, "red": 0}, "penalty": {"won": 1, "commited": null, "scored": 0, "missed": 0, "saved": null}}]}, {"player": {"id": 2937, "name": "Declan Rice", "photo": "https://media.api-sports.io/football/players/2937.png"}, "statistics": [{"games": {"minutes": 90, "number": 4, "position": "M", "rating": "9.3", "captain": true, "substitute": false}, "offsides": null, "shots": {"total": 1, "on": 1}, "goals": {"total": 1, "conceded": 0, "assists": 1, "saves": null}, "passes": {"total": 91, "key": 2, "accuracy": "87"}, "tackles": {"total": 7, "blocks": 2, "interceptions": 3}, "duels": {"total": 9, "won": 7}, "dribbles": {"attempts": null, "success": null, "past": 1}, "fouls": {"drawn": null, "committed": 1}, "cards": {"yellow": 0, "red": 0}, "penalty": {"won": null, "commited": null, "scored": 0, "missed": 0, "saved": null}}]}, {"player": {"id": 1460, "name": "Bukayo Saka", "photo": "https://media.api-sports.io/football/players/1460.png"}, "statistics": [{"games": {"minutes": 90, "number": 7, "position": "M", "rating": "9.3", "captain": false, "substitute": false}, "offsides": 1, "shots": {"total": 4, "on": 4}, "goals": {"total": 3, "conceded": 0, "assists": 0, "saves": null}, "passes": {"total": 23, "key": 3, "accuracy": "18"}, "tackles": {"total": 3, "blocks": null, "interceptions": null}, "duels": {"total": 11, "won": 6}, "dribbles": {"attempts": 1, "success": 1, "past": null}, "fouls": {"drawn": 2, "committed": null}, "cards": {"yellow": 0, "red": 0}, "penalty": {"won": null, "commited": null, "scored": 1, "missed": 0, "saved": null}}]}, {"player": {"id": 19170, "name": "Morgan Rogers", "photo": "https://media.api-sports.io/football/players/19170.png"}, "statistics": [{"games": {"minutes": 90, "number": 17, "position": "M", "rating": "6.7", "captain": false, "substitute": false}, "offsides": null, "shots": {"total": null, "on": null}, "goals": {"total": null, "conceded": 0, "assists": 0, "saves": null}, "passes": {"total": 42, "key": 3, "accuracy": "38"}, "tackles": {"total": 1, "blocks": null, "interceptions": null}, "duels": {"total": 9, "won": 5}, "dribbles": {"attempts": 3, "success": 2, "past": 2}, "fouls": {"drawn": 2, "committed": null}, "cards": {"yellow": 0, "red": 0}, "penalty": {"won": null, "commited": null, "scored": 0, "missed": 0, "saved": null}}]}, {"player": {"id": 19586, "name": "Eberechi Eze", "photo": "https://media.api-sports.io/football/players/19586.png"}, "statistics": [{"games": {"minutes": 79, "number": 21, "position": "M", "rating": "7.3", "captain": false, "substitute": false}, "offsides": null, "shots": {"total": 1, "on": null}, "goals": {"total": null, "conceded": 0, "assists": 1, "saves": null}, "passes": {"total": 56, "key": 2, "accuracy": "56"}, "tackles": {"total": null, "blocks": null, "interceptions": null}, "duels": {"total": 5, "won": 4}, "dribbles": {"attempts": 3, "success": 3, "past": null}, "fouls": {"drawn": 1, "committed": 1}, "cards": {"yellow": 0, "red": 0}, "penalty": {"won": null, "commited": null, "scored": 0, "missed": 0, "saved": null}}]}, {"player": {"id": 909, "name": "Marcus Rashford", "photo": "https://media.api-sports.io/football/players/909.png"}, "statistics": [{"games": {"minutes": 45, "number": 11, "position": "M", "rating": "6.9", "captain": false, "substitute": false}, "offsides": null, "shots": {"total": 2, "on": 2}, "goals": {"total": null, "conceded": 0, "assists": 1, "saves": null}, "passes": {"total": 20, "key": 3, "accuracy": "18"}, "tackles": {"total": null, "blocks": null, "interceptions": null}, "duels": {"total": 4, "won": 2}, "dribbles": {"attempts": 3, "success": 2, "past": null}, "fouls": {"drawn": null, "committed": null}, "cards": {"yellow": 0, "red": 0}, "penalty": {"won": null, "commited": null, "scored": 0, "missed": 0, "saved": null}}]}, {"player": {"id": 19974, "name": "Ivan Toney", "photo": "https://media.api-sports.io/football/players/19974.png"}, "statistics": [{"games": {"minutes": 79, "number": 22, "position": "F", "rating": "6.9", "captain": false, "substitute": false}, "offsides": 2, "shots": {"total": 1, "on": 1}, "goals": {"total": null, "conceded": 0, "assists": 0, "saves": null}, "passes": {"total": 18, "key": null, "accuracy": "14"}, "tackles": {"total": 2, "blocks": null, "interceptions": null}, "duels": {"total": 10, "won": 6}, "dribbles": {"attempts": null, "success": null, "past": null}, "fouls": {"drawn": 3, "committed": null}, "cards": {"yellow": 0, "red": 0}, "penalty": {"won": null, "commited": null, "scored": 0, "missed": 0, "saved": null}}]}, {"player": {"id": 19366, "name": "Ollie Watkins", "photo": "https://media.api-sports.io/football/players/19366.png"}, "statistics": [{"games": {"minutes": 45, "number": 19, "position": "F", "rating": "6.2", "captain": false, "substitute": true}, "offsides": null, "shots": {"total": 1, "on": null}, "goals": {"total": null, "conceded": 0, "assists": 0, "saves": null}, "passes": {"total": 11, "key": 2, "accuracy": "9"}, "tackles": {"total": 1, "blocks": null, "interceptions": null}, "duels": {"total": 10, "won": 4}, "dribbles": {"attempts": 3, "success": 2, "past": null}, "fouls": {"drawn": null, "committed": 1}, "cards": {"yellow": 0, "red": 0}, "penalty": {"won": null, "commited": null, "scored": 0, "missed": 0, "saved": null}}]}, {"player": {"id": 138908, "name": "Elliot Anderson", "photo": "https://media.api-sports.io/football/players/138908.png"}, "statistics": [{"games": {"minutes": 11, "number": 8, "position": "M", "rating": "6.3", "captain": false, "substitute": true}, "offsides": null, "shots": {"total": null, "on": null}, "goals": {"total": null, "conceded": 0, "assists": 0, "saves": null}, "passes": {"total": 11, "key": null, "accuracy": "11"}, "tackles": {"total": 1, "blocks": null, "interceptions": null}, "duels": {"total": 2, "won": 1}, "dribbles": {"attempts": null, "success": null, "past": null}, "fouls": {"drawn": null, "committed": null}, "cards": {"yellow": 0, "red": 0}, "penalty": {"won": null, "commited": null, "scored": 0, "missed": 0, "saved": null}}]}, {"player": {"id": 129718, "name": "Jude Bellingham", "photo": "https://media.api-sports.io/football/players/129718.png"}, "statistics": [{"games": {"minutes": 11, "number": 10, "position": "M", "rating": "8.3", "captain": false, "substitute": true}, "offsides": null, "shots": {"total": 2, "on": 2}, "goals": {"total": 1, "conceded": 0, "assists": 0, "saves": null}, "passes": {"total": 8, "key": null, "accuracy": "5"}, "tackles": {"total": null, "blocks": null, "interceptions": null}, "duels": {"total": 8, "won": 6}, "dribbles": {"attempts": 5, "success": 5, "past": 1}, "fouls": {"drawn": 1, "committed": null}, "cards": {"yellow": 0, "red": 0}, "penalty": {"won": null, "commited": null, "scored": 0, "missed": 0, "saved": null}}]}, {"player": {"id": 19545, "name": "Reece James", "photo": "https://media.api-sports.io/football/players/19545.png"}, "statistics": [{"games": {"minutes": 16, "number": 24, "position": "D", "rating": "6.7", "captain": false, "substitute": true}, "offsides": null, "shots": {"total": null, "on": null}, "goals": {"total": null, "conceded": 0, "assists": 0, "saves": null}, "passes": {"total": 2, "key": null, "accuracy": "2"}, "tackles": {"total": 1, "blocks": 1, "interceptions": 1}, "duels": {"total": 2, "won": 2}, "dribbles": {"attempts": 1, "success": 1, "past": null}, "fouls": {"drawn": null, "committed": null}, "cards": {"yellow": 0, "red": 0}, "penalty": {"won": null, "commited": null, "scored": 0, "missed": 0, "saved": null}}]}, {"player": {"id": 19720, "name": "Trevoh Chalobah", "photo": "https://media.api-sports.io/football/players/19720.png"}, "statistics": [{"games": {"minutes": 1, "number": 12, "position": "D", "rating": null, "captain": false, "substitute": true}, "offsides": null, "shots": {"total": null, "on": null}, "goals": {"total": null, "conceded": 0, "assists": 0, "saves": null}, "passes": {"total": null, "key": null, "accuracy": null}, "tackles": {"total": null, "blocks": null, "interceptions": null}, "duels": {"total": 1, "won": null}, "dribbles": {"attempts": null, "success": null, "past": 1}, "fouls": {"drawn": null, "committed": null}, "cards": {"yellow": 0, "red": 0}, "penalty": {"won": null, "commited": null, "scored": 0, "missed": 0, "saved": null}}]}, {"player": {"id": 162489, "name": "James Trafford", "photo": "https://media.api-sports.io/football/players/162489.png"}, "statistics": [{"games": {"minutes": null, "number": 23, "position": "G", "rating": null, "captain": false, "substitute": true}, "offsides": null, "shots": {"total": null, "on": null}, "goals": {"total": null, "conceded": 0, "assists": null, "saves": null}, "passes": {"total": null, "key": null, "accuracy": null}, "tackles": {"total": null, "blocks": null, "interceptions": null}, "duels": {"total": null, "won": null}, "dribbles": {"attempts": null, "success": null, "past": null}, "fouls": {"drawn": null, "committed": null}, "cards": {"yellow": 0, "red": 0}, "penalty": {"won": null, "commited": null, "scored": 0, "missed": 0, "saved": null}}]}, {"player": {"id": 2932, "name": "Jordan Pickford", "photo": "https://media.api-sports.io/football/players/2932.png"}, "statistics": [{"games": {"minutes": null, "number": 1, "position": "G", "rating": null, "captain": false, "substitute": true}, "offsides": null, "shots": {"total": null, "on": null}, "goals": {"total": null, "conceded": 0, "assists": null, "saves": null}, "passes": {"total": null, "key": null, "accuracy": null}, "tackles": {"total": null, "blocks": null, "interceptions": null}, "duels": {"total": null, "won": null}, "dribbles": {"attempts": null, "success": null, "past": null}, "fouls": {"drawn": null, "committed": null}, "cards": {"yellow": 0, "red": 0}, "penalty": {"won": null, "commited": null, "scored": 0, "missed": 0, "saved": null}}]}, {"player": {"id": 18961, "name": "Dan Burn", "photo": "https://media.api-sports.io/football/players/18961.png"}, "statistics": [{"games": {"minutes": null, "number": 15, "position": "D", "rating": null, "captain": false, "substitute": true}, "offsides": null, "shots": {"total": null, "on": null}, "goals": {"total": null, "conceded": 0, "assists": null, "saves": null}, "passes": {"total": null, "key": null, "accuracy": null}, "tackles": {"total": null, "blocks": null, "interceptions": null}, "duels": {"total": null, "won": null}, "dribbles": {"attempts": null, "success": null, "past": null}, "fouls": {"drawn": null, "committed": null}, "cards": {"yellow": 0, "red": 0}, "penalty": {"won": null, "commited": null, "scored": 0, "missed": 0, "saved": null}}]}, {"player": {"id": 626, "name": "John Stones", "photo": "https://media.api-sports.io/football/players/626.png"}, "statistics": [{"games": {"minutes": null, "number": 5, "position": "D", "rating": null, "captain": false, "substitute": true}, "offsides": null, "shots": {"total": null, "on": null}, "goals": {"total": null, "conceded": 0, "assists": null, "saves": null}, "passes": {"total": null, "key": null, "accuracy": null}, "tackles": {"total": null, "blocks": null, "interceptions": null}, "duels": {"total": null, "won": null}, "dribbles": {"attempts": null, "success": null, "past": null}, "fouls": {"drawn": null, "committed": null}, "cards": {"yellow": 0, "red": 0}, "penalty": {"won": null, "commited": null, "scored": 0, "missed": 0, "saved": null}}]}, {"player": {"id": 307123, "name": "Nico O'Reilly", "photo": "https://media.api-sports.io/football/players/307123.png"}, "statistics": [{"games": {"minutes": null, "number": 3, "position": "D", "rating": null, "captain": false, "substitute": true}, "offsides": null, "shots": {"total": null, "on": null}, "goals": {"total": null, "conceded": 0, "assists": null, "saves": null}, "passes": {"total": null, "key": null, "accuracy": null}, "tackles": {"total": null, "blocks": null, "interceptions": null}, "duels": {"total": null, "won": null}, "dribbles": {"attempts": null, "success": null, "past": null}, "fouls": {"drawn": null, "committed": null}, "cards": {"yellow": 0, "red": 0}, "penalty": {"won": null, "commited": null, "scored": 0, "missed": 0, "saved": null}}]}, {"player": {"id": 292, "name": "Jordan Henderson", "photo": "https://media.api-sports.io/football/players/292.png"}, "statistics": [{"games": {"minutes": null, "number": 14, "position": "M", "rating": null, "captain": false, "substitute": true}, "offsides": null, "shots": {"total": null, "on": null}, "goals": {"total": null, "conceded": 0, "assists": null, "saves": null}, "passes": {"total": null, "key": null, "accuracy": null}, "tackles": {"total": null, "blocks": null, "interceptions": null}, "duels": {"total": null, "won": null}, "dribbles": {"attempts": null, "success": null, "past": null}, "fouls": {"drawn": null, "committed": null}, "cards": {"yellow": 0, "red": 0}, "penalty": {"won": null, "commited": null, "scored": 0, "missed": 0, "saved": null}}]}, {"player": {"id": 138787, "name": "Anthony Gordon", "photo": "https://media.api-sports.io/football/players/138787.png"}, "statistics": [{"games": {"minutes": null, "number": 18, "position": "F", "rating": null, "captain": false, "substitute": true}, "offsides": null, "shots": {"total": null, "on": null}, "goals": {"total": null, "conceded": 0, "assists": null, "saves": null}, "passes": {"total": null, "key": null, "accuracy": null}, "tackles": {"total": null, "blocks": null, "interceptions": null}, "duels": {"total": null, "won": null}, "dribbles": {"attempts": null, "success": null, "past": null}, "fouls": {"drawn": null, "committed": null}, "cards": {"yellow": 0, "red": 0}, "penalty": {"won": null, "commited": null, "scored": 0, "missed": 0, "saved": null}}]}, {"player": {"id": 184, "name": "Harry Kane", "photo": "https://media.api-sports.io/football/players/184.png"}, "statistics": [{"games": {"minutes": null, "number": 9, "position": "F", "rating": null, "captain": false, "substitute": true}, "offsides": null, "shots": {"total": null, "on": null}, "goals": {"total": null, "conceded": 0, "assists": null, "saves": null}, "passes": {"total": null, "key": null, "accuracy": null}, "tackles": {"total": null, "blocks": null, "interceptions": null}, "duels": {"total": null, "won": null}, "dribbles": {"attempts": null, "success": null, "past": null}, "fouls": {"drawn": null, "committed": null}, "cards": {"yellow": 0, "red": 0}, "penalty": {"won": null, "commited": null, "scored": 0, "missed": 0, "saved": null}}]}, {"player": {"id": 136723, "name": "Noni Madueke", "photo": "https://media.api-sports.io/football/players/136723.png"}, "statistics": [{"games": {"minutes": null, "number": 20, "position": "F", "rating": null, "captain": false, "substitute": true}, "offsides": null, "shots": {"total": null, "on": null}, "goals": {"total": null, "conceded": 0, "assists": null, "saves": null}, "passes": {"total": null, "key": null, "accuracy": null}, "tackles": {"total": null, "blocks": null, "interceptions": null}, "duels": {"total": null, "won": null}, "dribbles": {"attempts": null, "success": null, "past": null}, "fouls": {"drawn": null, "committed": null}, "cards": {"yellow": 0, "red": 0}, "penalty": {"won": null, "commited": null, "scored": 0, "missed": 0, "saved": null}}]}]}]}